{"tracks":{"href":"https://api.spotify.com/v1/search?query=complicated&type=track&offset=0&limit=20","items":[{"album":{"album_type":"album","artists":[{"external_urls":{"spotify":"https://open.spotify.com/artist/0p4nmQO2msCgU4IF37Wi3j"},"href":"https://api.spotify.com/v1/artists/0p4nmQO2msCgU4IF37Wi3j","id":"0p4nmQO2msCgU4IF37Wi3j","name":"Avril Lavigne","type":"artist","uri":"spotify:artist:0p4nmQO2msCgU4IF37Wi3j"}],"available_markets":["AD","AR","AT","AU","BE","BG","BO","BR","CA","CH","CL","CO","CR","CY","CZ","DE","DK","DO","EC","EE","ES","FI","FR","GB","GR","GT","HK","HN","HU","ID","IE","IL","IS","IT","JP","LI","LT","LU","LV","MC","MT","MX","MY","NI","NL","NO","NZ","PA","PE","PH","PL","PT","PY","RO","SE","SG","SK","SV","TH","TR","TW","US","UY","VN","ZA"],"external_urls":{"spotify":"https://open.spotify.com/album/3zXjR3y2dUWklKmmp6lEhy"},"href":"https://api.spotify.com/v1/albums/3zXjR3y2dUWklKmmp6lEhy","id":"3zXjR3y2dUWklKmmp6lEhy","images":[{"height":640,"url":"https://i.scdn.co/image/710d4bcc4ea3ef54fe1408d8b979d54aa0b19f5d","width":640},{"height":300,"url":"https://i.scdn.co/image/89cfeeb1db8f972a0a53cf48f14728723508fcea","width":300},{"height":64,"url":"https://i.scdn.co/image/7557328d85eb0241350e525e773d0dac8d3678ed","width":64}],"name":"Let Go","release_date":"2002-09-06","release_date_precision":"day","total_tracks":13,"type":"album","uri":"spotify:album:3zXjR3y2dUWklKmmp6lEhy"},"artists":[{"external_urls":{"spotify":"https://open.spotify.com/artist/0p4nmQO2msCgU4IF37Wi3j"},"href":"https://api.spotify.com/v1/artists/0p4nmQO2msCgU4IF37Wi3j","id":"0p4nmQO2msCgU4IF37Wi3j","name":"Avril Lavigne","type":"artist","uri":"spotify:artist:0p4nmQO2msCgU4IF37Wi3j"}],"available_markets":["AD","AR","AT","AU","BE","BG","BO","BR","CA","CH","CL","CO","CR","CY","CZ","DE","DK","DO","EC","EE","ES","FI","FR","GB","GR","GT","HK","HN","HU","ID","IE","IL","IS","IT","JP","LI","LT","LU","LV","MC","MT","MX","MY","NI","NL","NO","NZ","PA","PE","PH","PL","PT","PY","RO","SE","SG","SK","SV","TH","TR","TW","US","UY","VN","ZA"],"disc_number":1,"duration_ms":244506,"explicit":false,"external_ids":{"isrc":"USAR10200223"},"external_urls":{"spotify":"https://open.spotify.com/track/5xEM5hIgJ1jjgcEBfpkt2F"},"href":"https://api.spotify.com/v1/tracks/5xEM5hIgJ1jjgcEBfpkt2F","id":"5xEM5hIgJ1jjgcEBfpkt2F","is_local":false,"name":"Complicated","popularity":77,"preview_url":"https://p.scdn.co/mp3-preview/497f3eed8dedf972b878e04e4e3f6b18556226c3?cid=d0ef11b08e9041258a97e4c3a1dc69ab","track_number":2,"type":"track","uri":"spotify:track:5xEM5hIgJ1jjgcEBfpkt2F"},{"album":{"album_type":"single","artists":[{"external_urls":{"spotify":"https://open.spotify.com/artist/1QRj3hoop9Mv5VvHQkwPEp"},"href":"https://api.spotify.com/v1/artists/1QRj3hoop9Mv5VvHQkwPEp","id":"1QRj3hoop9Mv5VvHQkwPEp","name":"Olivia O'Brien","type":"artist","uri":"spotify:artist:1QRj3hoop9Mv5VvHQkwPEp"}],"available_markets":["AD","AR","AT","AU","BE","BG","BO","BR","CA","CH","CL","CO","CR","CY","CZ","DE","DK","DO","EC","EE","ES","FI","FR","GB","GR","GT","HK","HN","HU","ID","IE","IL","IS","IT","JP","LI","LT","LU","LV","MC","MT","MX","MY","NI","NL","NO","NZ","PA","PE","PH","PL","PT","PY","RO","SE","SG","SK","SV","TH","TR","TW","US","UY","VN","ZA"],"external_urls":{"spotify":"https://open.spotify.com/album/18IaOJpyXfqbOsZIqmnfpZ"},"href":"https://api.spotify.com/v1/albums/18IaOJpyXfqbOsZIqmnfpZ","id":"18IaOJpyXfqbOsZIqmnfpZ","images":[{"height":640,"url":"https://i.scdn.co/image/fc3e7f2cd17a0a533fe04fab35d19dce222b404a","width":640},{"height":300,"url":"https://i.scdn.co/image/2f47cdfda049ef3157ed1200864ad091bf269602","width":300},{"height":64,"url":"https://i.scdn.co/image/563e1b94d23b31e64076bf8a93aa0fc905a4fe65","width":64}],"name":"Complicated","release_date":"2015-08-09","release_date_precision":"day","total_tracks":1,"type":"album","uri":"spotify:album:18IaOJpyXfqbOsZIqmnfpZ"},"artists":[{"external_urls":{"spotify":"https://open.spotify.com/artist/1QRj3hoop9Mv5VvHQkwPEp"},"href":"https://api.spotify.com/v1/artists/1QRj3hoop9Mv5VvHQkwPEp","id":"1QRj3hoop9Mv5VvHQkwPEp","name":"Olivia O'Brien","type":"artist","uri":"spotify:artist:1QRj3hoop9Mv5VvHQkwPEp"}],"available_markets":["AD","AR","AT","AU","BE","BG","BO","BR","CA","CH","CL","CO","CR","CY","CZ","DE","DK","DO","EC","EE","ES","FI","FR","GB","GR","GT","HK","HN","HU","ID","IE","IL","IS","IT","JP","LI","LT","LU","LV","MC","MT","MX","MY","NI","NL","NO","NZ","PA","PE","PH","PL","PT","PY","RO","SE","SG","SK","SV","TH","TR","TW","US","UY","VN","ZA"],"disc_number":1,"duration_ms":189000,"explicit":false,"external_ids":{"isrc":"QM4DW1576091"},"external_urls":{"spotify":"https://open.spotify.com/track/0jllH0usRFD4LJkJnGK9Lf"},"href":"https://api.spotify.com/v1/tracks/0jllH0usRFD4LJkJnGK9Lf","id":"0jllH0usRFD4LJkJnGK9Lf","is_local":false,"name":"Complicated","popularity":73,"preview_url":"https://p.scdn.co/mp3-preview/ed51ea9fb68f27a420dbaad3aa0ec944b2a4a150?cid=d0ef11b08e9041258a97e4c3a1dc69ab","track_number":1,"type":"track","uri":"spotify:track:0jllH0usRFD4LJkJnGK9Lf"},{"album":{"album_type":"album","artists":[{"external_urls":{"spotify":"https://open.spotify.com/artist/4Rxn7Im3LGfyRkY2FlHhWi"},"href":"https://api.spotify.com/v1/artists/4Rxn7Im3LGfyRkY2FlHhWi","id":"4Rxn7Im3LGfyRkY2FlHhWi","name":"Nick Jonas","type":"artist","uri":"spotify:artist:4Rxn7Im3LGfyRkY2FlHhWi"}],"available_markets":["AD","AR","AT","AU","BE","BG","BO","BR","CA","CH","CL","CO","CR","CY","CZ","DE","DK","DO","EC","EE","ES","FI","FR","GB","GR","GT","HK","HN","HU","ID","IE","IL","IS","IT","JP","LI","LT","LU","LV","MC","MT","MX","MY","NI","NL","NO","NZ","PA","PE","PH","PL","PT","PY","RO","SG","SK","SV","TH","TR","TW","US","UY","VN","ZA"],"external_urls":{"spotify":"https://open.spotify.com/album/4Yww2EYetseL1eL2YuvLna"},"href":"https://api.spotify.com/v1/albums/4Yww2EYetseL1eL2YuvLna","id":"4Yww2EYetseL1eL2YuvLna","images":[{"height":640,"url":"https://i.scdn.co/image/6639c2566040b01bbc89402ae57feb9ccee03bad","width":640},{"height":300,"url":"https://i.scdn.co/image/2405d73b6f44240342011b733f418b19dc4f7ec1","width":300},{"height":64,"url":"https://i.scdn.co/image/75ed356efc7c4bfe8c116ae79bce9ba27e92348f","width":64}],"name":"Last Year Was Complicated","release_date":"2016-06-10","release_date_precision":"day","total_tracks":12,"type":"album","uri":"spotify:album:4Yww2EYetseL1eL2YuvLna"},"artists":[{"external_urls":{"spotify":"https://open.spotify.com/artist/4Rxn7Im3LGfyRkY2FlHhWi"},"href":"https://api.spotify.com/v1/artists/4Rxn7Im3LGfyRkY2FlHhWi","id":"4Rxn7Im3LGfyRkY2FlHhWi","name":"Nick Jonas","type":"artist","uri":"spotify:artist:4Rxn7Im3LGfyRkY2FlHhWi"},{"external_urls":{"spotify":"https://open.spotify.com/artist/4NHQUGzhtTLFvgF5SZesLK"},"href":"https://api.spotify.com/v1/artists/4NHQUGzhtTLFvgF5SZesLK","id":"4NHQUGzhtTLFvgF5SZesLK","name":"Tove Lo","type":"artist","uri":"spotify:artist:4NHQUGzhtTLFvgF5SZesLK"}],"available_markets":["AD","AR","AT","AU","BE","BG","BO","BR","CA","CH","CL","CO","CR","CY","CZ","DE","DK","DO","EC","EE","ES","FI","FR","GB","GR","GT","HK","HN","HU","ID","IE","IL","IS","IT","JP","LI","LT","LU","LV","MC","MT","MX","MY","NI","NL","NO","NZ","PA","PE","PH","PL","PT","PY","RO","SG","SK","SV","TH","TR","TW","US","UY","VN","ZA"],"disc_number":1,"duration_ms":234213,"explicit":false,"external_ids":{"isrc":"USUM71602394"},"external_urls":{"spotify":"https://open.spotify.com/track/3lSDIJ2abCrOdDJ6pshUap"},"href":"https://api.spotify.com/v1/tracks/3lSDIJ2abCrOdDJ6pshUap","id":"3lSDIJ2abCrOdDJ6pshUap","is_local":false,"name":"Close","popularity":71,"preview_url":null,"track_number":3,"type":"track","uri":"spotify:track:3lSDIJ2abCrOdDJ6pshUap"},{"album":{"album_type":"album","artists":[{"external_urls":{"spotify":"https://open.spotify.com/artist/5kmcKvoT2hRuXOGnjcXc8e"},"href":"https://api.spotify.com/v1/artists/5kmcKvoT2hRuXOGnjcXc8e","id":"5kmcKvoT2hRuXOGnjcXc8e","name":"MIKExANGEL","type":"artist","uri":"spotify:artist:5kmcKvoT2hRuXOGnjcXc8e"}],"available_markets":["AD","AR","AT","AU","BE","BG","BO","BR","CA","CH","CL","CO","CR","CY","CZ","DE","DK","DO","EC","EE","ES","FI","FR","GB","GR","GT","HK","HN","HU","ID","IE","IL","IS","IT","JP","LI","LT","LU","LV","MC","MT","MX","MY","NI","NL","NO","NZ","PA","PE","PH","PL","PT","PY","RO","SE","SG","SK","SV","TH","TR","TW","US","UY","VN","ZA"],"external_urls":{"spotify":"https://open.spotify.com/album/2hL1QtBuDgWpvkOD3FTdX5"},"href":"https://api.spotify.com/v1/albums/2hL1QtBuDgWpvkOD3FTdX5","id":"2hL1QtBuDgWpvkOD3FTdX5","images":[{"height":640,"url":"https://i.scdn.co/image/d66f7de6269fccc7179a6d75b36a8a753bef511f","width":640},{"height":300,"url":"https://i.scdn.co/image/43331bb97daad28aa1150c460e2489275f41ab75","width":300},{"height":64,"url":"https://i.scdn.co/image/707258add3a5eeeaf1c6518235adaf84c8da7fb0","width":64}],"name":"NOTHiN 2 SOMETHiN","release_date":"2017-06-09","release_date_precision":"day","total_tracks":10,"type":"album","uri":"spotify:album:2hL1QtBuDgWpvkOD3FTdX5"},"artists":[{"external_urls":{"spotify":"https://open.spotify.com/artist/5kmcKvoT2hRuXOGnjcXc8e"},"href":"https://api.spotify.com/v1/artists/5kmcKvoT2hRuXOGnjcXc8e","id":"5kmcKvoT2hRuXOGnjcXc8e","name":"MIKExANGEL","type":"artist","uri":"spotify:artist:5kmcKvoT2hRuXOGnjcXc8e"}],"available_markets":["AD","AR","AT","AU","BE","BG","BO","BR","CA","CH","CL","CO","CR","CY","CZ","DE","DK","DO","EC","EE","ES","FI","FR","GB","GR","GT","HK","HN","HU","ID","IE","IL","IS","IT","JP","LI","LT","LU","LV","MC","MT","MX","MY","NI","NL","NO","NZ","PA","PE","PH","PL","PT","PY","RO","SE","SG","SK","SV","TH","TR","TW","US","UY","VN","ZA"],"disc_number":1,"duration_ms":192984,"explicit":true,"external_ids":{"isrc":"QMCE31701154"},"external_urls":{"spotify":"https://open.spotify.com/track/5cKRlX4h9UqSOBIuNZfsvP"},"href":"https://api.spotify.com/v1/tracks/5cKRlX4h9UqSOBIuNZfsvP","id":"5cKRlX4h9UqSOBIuNZfsvP","is_local":false,"name":"Complicated","popularity":62,"preview_url":"https://p.scdn.co/mp3-preview/0bdad29ba90d2e36d4c598ebe183d441a212074b?cid=d0ef11b08e9041258a97e4c3a1dc69ab","track_number":6,"type":"track","uri":"spotify:track:5cKRlX4h9UqSOBIuNZfsvP"},{"album":{"album_type":"album","artists":[{"external_urls":{"spotify":"https://open.spotify.com/artist/4Rxn7Im3LGfyRkY2FlHhWi"},"href":"https://api.spotify.com/v1/artists/4Rxn7Im3LGfyRkY2FlHhWi","id":"4Rxn7Im3LGfyRkY2FlHhWi","name":"Nick Jonas","type":"artist","uri":"spotify:artist:4Rxn7Im3LGfyRkY2FlHhWi"}],"available_markets":["AD","AR","AT","AU","BE","BG","BO","BR","CA","CH","CL","CO","CR","CY","CZ","DE","DK","DO","EC","EE","ES","FI","FR","GB","GR","GT","HK","HN","HU","ID","IE","IL","IS","IT","JP","LI","LT","LU","LV","MC","MT","MX","MY","NI","NL","NO","NZ","PA","PE","PH","PL","PT","PY","RO","SG","SK","SV","TH","TR","TW","US","UY","VN","ZA"],"external_urls":{"spotify":"https://open.spotify.com/album/4Yww2EYetseL1eL2YuvLna"},"href":"https://api.spotify.com/v1/albums/4Yww2EYetseL1eL2YuvLna","id":"4Yww2EYetseL1eL2YuvLna","images":[{"height":640,"url":"https://i.scdn.co/image/6639c2566040b01bbc89402ae57feb9ccee03bad","width":640},{"height":300,"url":"https://i.scdn.co/image/2405d73b6f44240342011b733f418b19dc4f7ec1","width":300},{"height":64,"url":"https://i.scdn.co/image/75ed356efc7c4bfe8c116ae79bce9ba27e92348f","width":64}],"name":"Last Year Was Complicated","release_date":"2016-06-10","release_date_precision":"day","total_tracks":12,"type":"album","uri":"spotify:album:4Yww2EYetseL1eL2YuvLna"},"artists":[{"external_urls":{"spotify":"https://open.spotify.com/artist/4Rxn7Im3LGfyRkY2FlHhWi"},"href":"https://api.spotify.com/v1/artists/4Rxn7Im3LGfyRkY2FlHhWi","id":"4Rxn7Im3LGfyRkY2FlHhWi","name":"Nick Jonas","type":"artist","uri":"spotify:artist:4Rxn7Im3LGfyRkY2FlHhWi"}],"available_markets":["AD","AR","AT","AU","BE","BG","BO","BR","CA","CH","CL","CO","CR","CY","CZ","DE","DK","DO","EC","EE","ES","FI","FR","GB","GR","GT","HK","HN","HU","ID","IE","IL","IS","IT","JP","LI","LT","LU","LV","MC","MT","MX","MY","NI","NL","NO","NZ","PA","PE","PH","PL","PT","PY","RO","SG","SK","SV","TH","TR","TW","US","UY","VN","ZA"],"disc_number":1,"duration_ms":199520,"explicit":true,"external_ids":{"isrc":"USUM71602395"},"external_urls":{"spotify":"https://open.spotify.com/track/5UsW4W8VgHrRLDzXQ9XSpt"},"href":"https://api.spotify.com/v1/tracks/5UsW4W8VgHrRLDzXQ9XSpt","id":"5UsW4W8VgHrRLDzXQ9XSpt","is_local":false,"name":"Chainsaw","popularity":70,"preview_url":null,"track_number":4,"type":"track","uri":"spotify:track:5UsW4W8VgHrRLDzXQ9XSpt"},{"album":{"album_type":"single","artists":[{"external_urls":{"spotify":"https://open.spotify.com/artist/5Q81rlcTFh3k6DQJXPdsot"},"href":"https://api.spotify.com/v1/artists/5Q81rlcTFh3k6DQJXPdsot","id":"5Q81rlcTFh3k6DQJXPdsot","name":"Mura Masa","type":"artist","uri":"spotify:artist:5Q81rlcTFh3k6DQJXPdsot"},{"external_urls":{"spotify":"https://open.spotify.com/artist/7aFTOGFDEqDtJUCziLVsVC"},"href":"https://api.spotify.com/v1/artists/7aFTOGFDEqDtJUCziLVsVC","id":"7aFTOGFDEqDtJUCziLVsVC","name":"Nao","type":"artist","uri":"spotify:artist:7aFTOGFDEqDtJUCziLVsVC"}],"available_markets":["AD","AR","AT","AU","BE","BG","BO","BR","CA","CH","CL","CO","CR","CY","CZ","DE","DK","DO","EC","EE","ES","FI","FR","GB","GR","GT","HK","HN","HU","ID","IE","IL","IS","IT","JP","LI","LT","LU","LV","MC","MT","MX","MY","NI","NL","NO","NZ","PA","PE","PH","PL","PT","PY","RO","SE","SG","SK","SV","TH","TR","TW","US","UY","VN","ZA"],"external_urls":{"spotify":"https://open.spotify.com/album/5nPFqFsQU6S0F5eWYtVU2b"},"href":"https://api.spotify.com/v1/albums/5nPFqFsQU6S0F5eWYtVU2b","id":"5nPFqFsQU6S0F5eWYtVU2b","images":[{"height":640,"url":"https://i.scdn.co/image/a999d18c06eaf887acbe4ebf31e13ae5bbcc8ba1","width":640},{"height":300,"url":"https://i.scdn.co/image/55909627e3f057040d468dedb8925552519e2c68","width":300},{"height":64,"url":"https://i.scdn.co/image/10b60771315d43e7215ac769c82750cd98a817dc","width":64}],"name":"Complicated","release_date":"2018-08-02","release_date_precision":"day","total_tracks":1,"type":"album","uri":"spotify:album:5nPFqFsQU6S0F5eWYtVU2b"},"artists":[{"external_urls":{"spotify":"https://open.spotify.com/artist/5Q81rlcTFh3k6DQJXPdsot"},"href":"https://api.spotify.com/v1/artists/5Q81rlcTFh3k6DQJXPdsot","id":"5Q81rlcTFh3k6DQJXPdsot","name":"Mura Masa","type":"artist","uri":"spotify:artist:5Q81rlcTFh3k6DQJXPdsot"},{"external_urls":{"spotify":"https://open.spotify.com/artist/7aFTOGFDEqDtJUCziLVsVC"},"href":"https://api.spotify.com/v1/artists/7aFTOGFDEqDtJUCziLVsVC","id":"7aFTOGFDEqDtJUCziLVsVC","name":"Nao","type":"artist","uri":"spotify:artist:7aFTOGFDEqDtJUCziLVsVC"}],"available_markets":["AD","AR","AT","AU","BE","BG","BO","BR","CA","CH","CL","CO","CR","CY","CZ","DE","DK","DO","EC","EE","ES","FI","FR","GB","GR","GT","HK","HN","HU","ID","IE","IL","IS","IT","JP","LI","LT","LU","LV","MC","MT","MX","MY","NI","NL","NO","NZ","PA","PE","PH","PL","PT","PY","RO","SE","SG","SK","SV","TH","TR","TW","US","UY","VN","ZA"],"disc_number":1,"duration_ms":213906,"explicit":false,"external_ids":{"isrc":"GBUM71804320"},"external_urls":{"spotify":"https://open.spotify.com/track/2mssuAa5xshIx2c06p1c2F"},"href":"https://api.spotify.com/v1/tracks/2mssuAa5xshIx2c06p1c2F","id":"2mssuAa5xshIx2c06p1c2F","is_local":false,"name":"Complicated","popularity":68,"preview_url":null,"track_number":1,"type":"track","uri":"spotify:track:2mssuAa5xshIx2c06p1c2F"},{"album":{"album_type":"album","artists":[{"external_urls":{"spotify":"https://open.spotify.com/artist/4Rxn7Im3LGfyRkY2FlHhWi"},"href":"https://api.spotify.com/v1/artists/4Rxn7Im3LGfyRkY2FlHhWi","id":"4Rxn7Im3LGfyRkY2FlHhWi","name":"Nick Jonas","type":"artist","uri":"spotify:artist:4Rxn7Im3LGfyRkY2FlHhWi"}],"available_markets":["AD","AR","AT","AU","BE","BG","BO","BR","CA","CH","CL","CO","CR","CY","CZ","DE","DK","DO","EC","EE","ES","FI","FR","GB","GR","GT","HK","HN","HU","ID","IE","IL","IS","IT","JP","LI","LT","LU","LV","MC","MT","MX","MY","NI","NL","NO","NZ","PA","PE","PH","PL","PT","PY","RO","SG","SK","SV","TH","TR","TW","US","UY","VN","ZA"],"external_urls":{"spotify":"https://open.spotify.com/album/4Yww2EYetseL1eL2YuvLna"},"href":"https://api.spotify.com/v1/albums/4Yww2EYetseL1eL2YuvLna","id":"4Yww2EYetseL1eL2YuvLna","images":[{"height":640,"url":"https://i.scdn.co/image/6639c2566040b01bbc89402ae57feb9ccee03bad","width":640},{"height":300,"url":"https://i.scdn.co/image/2405d73b6f44240342011b733f418b19dc4f7ec1","width":300},{"height":64,"url":"https://i.scdn.co/image/75ed356efc7c4bfe8c116ae79bce9ba27e92348f","width":64}],"name":"Last Year Was Complicated","release_date":"2016-06-10","release_date_precision":"day","total_tracks":12,"type":"album","uri":"spotify:album:4Yww2EYetseL1eL2YuvLna"},"artists":[{"external_urls":{"spotify":"https://open.spotify.com/artist/4Rxn7Im3LGfyRkY2FlHhWi"},"href":"https://api.spotify.com/v1/artists/4Rxn7Im3LGfyRkY2FlHhWi","id":"4Rxn7Im3LGfyRkY2FlHhWi","name":"Nick Jonas","type":"artist","uri":"spotify:artist:4Rxn7Im3LGfyRkY2FlHhWi"},{"external_urls":{"spotify":"https://open.spotify.com/artist/7c0XG5cIJTrrAgEC3ULPiq"},"href":"https://api.spotify.com/v1/artists/7c0XG5cIJTrrAgEC3ULPiq","id":"7c0XG5cIJTrrAgEC3ULPiq","name":"Ty Dolla $ign","type":"artist","uri":"spotify:artist:7c0XG5cIJTrrAgEC3ULPiq"}],"available_markets":["AD","AR","AT","AU","BE","BG","BO","BR","CA","CH","CL","CO","CR","CY","CZ","DE","DK","DO","EC","EE","ES","FI","FR","GB","GR","GT","HK","HN","HU","ID","IE","IL","IS","IT","JP","LI","LT","LU","LV","MC","MT","MX","MY","NI","NL","NO","NZ","PA","PE","PH","PL","PT","PY","RO","SG","SK","SV","TH","TR","TW","US","UY","VN","ZA"],"disc_number":1,"duration_ms":182946,"explicit":true,"external_ids":{"isrc":"USUM71602418"},"external_urls":{"spotify":"https://open.spotify.com/track/5W4vPDfwFNQqt7frRjL41t"},"href":"https://api.spotify.com/v1/tracks/5W4vPDfwFNQqt7frRjL41t","id":"5W4vPDfwFNQqt7frRjL41t","is_local":false,"name":"Bacon","popularity":65,"preview_url":null,"track_number":6,"type":"track","uri":"spotify:track:5W4vPDfwFNQqt7frRjL41t"},{"album":{"album_type":"single","artists":[{"external_urls":{"spotify":"https://open.spotify.com/artist/73jBynjsVtofjRpdpRAJGk"},"href":"https://api.spotify.com/v1/artists/73jBynjsVtofjRpdpRAJGk","id":"73jBynjsVtofjRpdpRAJGk","name":"Dimitri Vegas & Like Mike","type":"artist","uri":"spotify:artist:73jBynjsVtofjRpdpRAJGk"},{"external_urls":{"spotify":"https://open.spotify.com/artist/1Cs0zKBU1kc0i8ypK3B9ai"},"href":"https://api.spotify.com/v1/artists/1Cs0zKBU1kc0i8ypK3B9ai","id":"1Cs0zKBU1kc0i8ypK3B9ai","name":"David Guetta","type":"artist","uri":"spotify:artist:1Cs0zKBU1kc0i8ypK3B9ai"}],"available_markets":["AD","AR","AT","AU","BE","BG","BO","BR","CA","CH","CL","CO","CR","CY","CZ","DE","DK","DO","EC","EE","ES","FI","FR","GB","GR","GT","HK","HN","HU","ID","IE","IL","IS","IT","JP","LI","LT","LU","LV","MC","MT","MX","MY","NI","NL","NO","NZ","PA","PE","PH","PL","PT","PY","RO","SE","SG","SK","SV","TH","TR","TW","US","UY","VN","ZA"],"external_urls":{"spotify":"https://open.spotify.com/album/6SgTiW8a5BHFXbR03BteCd"},"href":"https://api.spotify.com/v1/albums/6SgTiW8a5BHFXbR03BteCd","id":"6SgTiW8a5BHFXbR03BteCd","images":[{"height":640,"url":"https://i.scdn.co/image/37bf5c4de8bc0f5b7eb43947842a788b70765766","width":640},{"height":300,"url":"https://i.scdn.co/image/e7e73238090cc89543dc05971e835657999d67bf","width":300},{"height":64,"url":"https://i.scdn.co/image/1690e0a5f05d0f70e0859216c99c75d6e8008779","width":64}],"name":"Complicated (feat. Kiiara)","release_date":"2017-07-28","release_date_precision":"day","total_tracks":1,"type":"album","uri":"spotify:album:6SgTiW8a5BHFXbR03BteCd"},"artists":[{"external_urls":{"spotify":"https://open.spotify.com/artist/73jBynjsVtofjRpdpRAJGk"},"href":"https://api.spotify.com/v1/artists/73jBynjsVtofjRpdpRAJGk","id":"73jBynjsVtofjRpdpRAJGk","name":"Dimitri Vegas & Like Mike","type":"artist","uri":"spotify:artist:73jBynjsVtofjRpdpRAJGk"},{"external_urls":{"spotify":"https://open.spotify.com/artist/1Cs0zKBU1kc0i8ypK3B9ai"},"href":"https://api.spotify.com/v1/artists/1Cs0zKBU1kc0i8ypK3B9ai","id":"1Cs0zKBU1kc0i8ypK3B9ai","name":"David Guetta","type":"artist","uri":"spotify:artist:1Cs0zKBU1kc0i8ypK3B9ai"},{"external_urls":{"spotify":"https://open.spotify.com/artist/4u5smJBskI6Adzv08PuiUP"},"href":"https://api.spotify.com/v1/artists/4u5smJBskI6Adzv08PuiUP","id":"4u5smJBskI6Adzv08PuiUP","name":"Kiiara","type":"artist","uri":"spotify:artist:4u5smJBskI6Adzv08PuiUP"}],"available_markets":["AD","AR","AT","AU","BE","BG","BO","BR","CA","CH","CL","CO","CR","CY","CZ","DE","DK","DO","EC","EE","ES","FI","FR","GB","GR","GT","HK","HN","HU","ID","IE","IL","IS","IT","JP","LI","LT","LU","LV","MC","MT","MX","MY","NI","NL","NO","NZ","PA","PE","PH","PL","PT","PY","RO","SE","SG","SK","SV","TH","TR","TW","US","UY","VN","ZA"],"disc_number":1,"duration_ms":184247,"explicit":false,"external_ids":{"isrc":"BEG851700001"},"external_urls":{"spotify":"https://open.spotify.com/track/1Sl3njkhhz8nrSPZroDQ82"},"href":"https://api.spotify.com/v1/tracks/1Sl3njkhhz8nrSPZroDQ82","id":"1Sl3njkhhz8nrSPZroDQ82","is_local":false,"name":"Complicated (feat. Kiiara)","popularity":72,"preview_url":"https://p.scdn.co/mp3-preview/f216a144f520dc58355afb4a43239d0bef381d55?cid=d0ef11b08e9041258a97e4c3a1dc69ab","track_number":1,"type":"track","uri":"spotify:track:1Sl3njkhhz8nrSPZroDQ82"},{"album":{"album_type":"album","artists":[{"external_urls":{"spotify":"https://open.spotify.com/artist/4NiJW4q9ichVqL1aUsgGAN"},"href":"https://api.spotify.com/v1/artists/4NiJW4q9ichVqL1aUsgGAN","id":"4NiJW4q9ichVqL1aUsgGAN","name":"A Day To Remember","type":"artist","uri":"spotify:artist:4NiJW4q9ichVqL1aUsgGAN"}],"available_markets":["AD","AR","AT","AU","BE","BG","BO","BR","CA","CH","CL","CO","CR","CY","CZ","DE","DK","DO","EC","EE","ES","FI","FR","GB","GR","GT","HK","HN","HU","ID","IE","IL","IS","IT","JP","LI","LT","LU","LV","MC","MT","MX","MY","NI","NL","NO","NZ","PA","PE","PH","PL","PT","PY","RO","SE","SG","SK","SV","TH","TR","TW","US","UY","VN","ZA"],"external_urls":{"spotify":"https://open.spotify.com/album/2kllnMabPw1hYID0MhQRK0"},"href":"https://api.spotify.com/v1/albums/2kllnMabPw1hYID0MhQRK0","id":"2kllnMabPw1hYID0MhQRK0","images":[{"height":640,"url":"https://i.scdn.co/image/9e6ec09914b7533d0ba773ea3b640cc19b4fc355","width":640},{"height":300,"url":"https://i.scdn.co/image/4eae1f7f41b4d59164528bf6972063cdd7ba1a8f","width":300},{"height":64,"url":"https://i.scdn.co/image/a0fdb529fc9ec0881310f643b785e4bf7cfeb2a2","width":64}],"name":"What Separates Me From You","release_date":"2011-10-01","release_date_precision":"day","total_tracks":10,"type":"album","uri":"spotify:album:2kllnMabPw1hYID0MhQRK0"},"artists":[{"external_urls":{"spotify":"https://open.spotify.com/artist/4NiJW4q9ichVqL1aUsgGAN"},"href":"https://api.spotify.com/v1/artists/4NiJW4q9ichVqL1aUsgGAN","id":"4NiJW4q9ichVqL1aUsgGAN","name":"A Day To Remember","type":"artist","uri":"spotify:artist:4NiJW4q9ichVqL1aUsgGAN"}],"available_markets":["AD","AR","AT","AU","BE","BG","BO","BR","CA","CH","CL","CO","CR","CY","CZ","DE","DK","DO","EC","EE","ES","FI","FR","GB","GR","GT","HK","HN","HU","ID","IE","IL","IS","IT","JP","LI","LT","LU","LV","MC","MT","MX","MY","NI","NL","NO","NZ","PA","PE","PH","PL","PT","PY","RO","SE","SG","SK","SV","TH","TR","TW","US","UY","VN","ZA"],"disc_number":1,"duration_ms":177240,"explicit":false,"external_ids":{"isrc":"USVIC1060303"},"external_urls":{"spotify":"https://open.spotify.com/track/069deq5woglvUnWok4MqTe"},"href":"https://api.spotify.com/v1/tracks/069deq5woglvUnWok4MqTe","id":"069deq5woglvUnWok4MqTe","is_local":false,"name":"It's Complicated","popularity":58,"preview_url":"https://p.scdn.co/mp3-preview/e76d88b82f01ac10c6c0f4dbfb79f08218c00cc6?cid=d0ef11b08e9041258a97e4c3a1dc69ab","track_number":3,"type":"track","uri":"spotify:track:069deq5woglvUnWok4MqTe"},{"album":{"album_type":"album","artists":[{"external_urls":{"spotify":"https://open.spotify.com/artist/15Dh5PvHQj909E0RgAe0aN"},"href":"https://api.spotify.com/v1/artists/15Dh5PvHQj909E0RgAe0aN","id":"15Dh5PvHQj909E0RgAe0aN","name":"Nivea","type":"artist","uri":"spotify:artist:15Dh5PvHQj909E0RgAe0aN"}],"available_markets":["AD","AR","BO","BR","CA","CL","CO","CR","DO","EC","FR","GB","GT","HK","HN","ID","IE","JP","MC","MX","MY","NI","PA","PE","PH","PY","SG","SV","TH","TW","US","UY","VN"],"external_urls":{"spotify":"https://open.spotify.com/album/3KNzGIMzjSY0x2HV3Lm53c"},"href":"https://api.spotify.com/v1/albums/3KNzGIMzjSY0x2HV3Lm53c","id":"3KNzGIMzjSY0x2HV3Lm53c","images":[{"height":640,"url":"https://i.scdn.co/image/e2fc38695d898c9a019b89e91eca3d8dbf1abd8b","width":640},{"height":300,"url":"https://i.scdn.co/image/dfdd6e519bba6ec5f3c30bf60e6ca69f68809c05","width":300},{"height":64,"url":"https://i.scdn.co/image/c8c07194e94863ea30a41539d8ef3618b2dd8116","width":64}],"name":"Complicated","release_date":"2001-01-01","release_date_precision":"day","total_tracks":14,"type":"album","uri":"spotify:album:3KNzGIMzjSY0x2HV3Lm53c"},"artists":[{"external_urls":{"spotify":"https://open.spotify.com/artist/15Dh5PvHQj909E0RgAe0aN"},"href":"https://api.spotify.com/v1/artists/15Dh5PvHQj909E0RgAe0aN","id":"15Dh5PvHQj909E0RgAe0aN","name":"Nivea","type":"artist","uri":"spotify:artist:15Dh5PvHQj909E0RgAe0aN"}],"available_markets":["AD","AR","BO","BR","CA","CL","CO","CR","DO","EC","FR","GB","GT","HK","HN","ID","IE","JP","MC","MX","MY","NI","PA","PE","PH","PY","SG","SV","TH","TW","US","UY","VN"],"disc_number":1,"duration_ms":232346,"explicit":false,"external_ids":{"isrc":"USJI10500108"},"external_urls":{"spotify":"https://open.spotify.com/track/0XHt0UmBzFJy1KKigTZ0tN"},"href":"https://api.spotify.com/v1/tracks/0XHt0UmBzFJy1KKigTZ0tN","id":"0XHt0UmBzFJy1KKigTZ0tN","is_local":false,"name":"Complicated","popularity":51,"preview_url":"https://p.scdn.co/mp3-preview/f4ab8040eb0886a1aeb9f42373be8e75f83e219c?cid=d0ef11b08e9041258a97e4c3a1dc69ab","track_number":2,"type":"track","uri":"spotify:track:0XHt0UmBzFJy1KKigTZ0tN"},{"album":{"album_type":"single","artists":[{"external_urls":{"spotify":"https://open.spotify.com/artist/67nwj3Y5sZQLl72VNUHEYE"},"href":"https://api.spotify.com/v1/artists/67nwj3Y5sZQLl72VNUHEYE","id":"67nwj3Y5sZQLl72VNUHEYE","name":"Wale","type":"artist","uri":"spotify:artist:67nwj3Y5sZQLl72VNUHEYE"}],"available_markets":["AD","AR","AT","AU","BE","BG","BO","BR","CA","CH","CL","CO","CR","CY","CZ","DE","DK","DO","EC","EE","ES","FI","FR","GB","GR","GT","HK","HN","HU","ID","IE","IL","IS","IT","JP","LI","LT","LU","LV","MC","MT","MX","MY","NI","NL","NO","NZ","PA","PE","PH","PL","PT","PY","RO","SE","SG","SK","SV","TH","TR","TW","US","UY","VN","ZA"],"external_urls":{"spotify":"https://open.spotify.com/album/73Nno1P5AhlkdmkieYeSiR"},"href":"https://api.spotify.com/v1/albums/73Nno1P5AhlkdmkieYeSiR","id":"73Nno1P5AhlkdmkieYeSiR","images":[{"height":640,"url":"https://i.scdn.co/image/330c65fb3f5697d187490f928bb47e0160579508","width":640},{"height":300,"url":"https://i.scdn.co/image/fdd83680909ff6aa121e35f33bca6529ede041a7","width":300},{"height":64,"url":"https://i.scdn.co/image/91649162b4c8330223366a62335f0e0d16e6ef04","width":64}],"name":"It's Complicated - EP","release_date":"2018-03-13","release_date_precision":"day","total_tracks":4,"type":"album","uri":"spotify:album:73Nno1P5AhlkdmkieYeSiR"},"artists":[{"external_urls":{"spotify":"https://open.spotify.com/artist/67nwj3Y5sZQLl72VNUHEYE"},"href":"https://api.spotify.com/v1/artists/67nwj3Y5sZQLl72VNUHEYE","id":"67nwj3Y5sZQLl72VNUHEYE","name":"Wale","type":"artist","uri":"spotify:artist:67nwj3Y5sZQLl72VNUHEYE"},{"external_urls":{"spotify":"https://open.spotify.com/artist/4tMm1dU6Gn04VAZ9ClHcIZ"},"href":"https://api.spotify.com/v1/artists/4tMm1dU6Gn04VAZ9ClHcIZ","id":"4tMm1dU6Gn04VAZ9ClHcIZ","name":"Jacquees","type":"artist","uri":"spotify:artist:4tMm1dU6Gn04VAZ9ClHcIZ"}],"available_markets":["AD","AR","AT","AU","BE","BG","BO","BR","CA","CH","CL","CO","CR","CY","CZ","DE","DK","DO","EC","EE","ES","FI","FR","GB","GR","GT","HK","HN","HU","ID","IE","IL","IS","IT","JP","LI","LT","LU","LV","MC","MT","MX","MY","NI","NL","NO","NZ","PA","PE","PH","PL","PT","PY","RO","SE","SG","SK","SV","TH","TR","TW","US","UY","VN","ZA"],"disc_number":1,"duration_ms":175525,"explicit":true,"external_ids":{"isrc":"USUYG1188142"},"external_urls":{"spotify":"https://open.spotify.com/track/6Tz7ibuxnLWQmWPVAzyaXu"},"href":"https://api.spotify.com/v1/tracks/6Tz7ibuxnLWQmWPVAzyaXu","id":"6Tz7ibuxnLWQmWPVAzyaXu","is_local":false,"name":"Black Bonnie (feat. Jacquees)","popularity":59,"preview_url":"https://p.scdn.co/mp3-preview/f8daf24157207250d1191a7777aed785bb252be1?cid=d0ef11b08e9041258a97e4c3a1dc69ab","track_number":2,"type":"track","uri":"spotify:track:6Tz7ibuxnLWQmWPVAzyaXu"},{"album":{"album_type":"album","artists":[{"external_urls":{"spotify":"https://open.spotify.com/artist/4Rxn7Im3LGfyRkY2FlHhWi"},"href":"https://api.spotify.com/v1/artists/4Rxn7Im3LGfyRkY2FlHhWi","id":"4Rxn7Im3LGfyRkY2FlHhWi","name":"Nick Jonas","type":"artist","uri":"spotify:artist:4Rxn7Im3LGfyRkY2FlHhWi"}],"available_markets":["AD","AR","AT","AU","BE","BG","BO","BR","CA","CH","CL","CO","CR","CY","CZ","DE","DK","DO","EC","EE","ES","FI","FR","GB","GR","GT","HK","HN","HU","ID","IE","IL","IS","IT","JP","LI","LT","LU","LV","MC","MT","MX","MY","NI","NL","NO","NZ","PA","PE","PH","PL","PT","PY","RO","SG","SK","SV","TH","TR","TW","US","UY","VN","ZA"],"external_urls":{"spotify":"https://open.spotify.com/album/4Yww2EYetseL1eL2YuvLna"},"href":"https://api.spotify.com/v1/albums/4Yww2EYetseL1eL2YuvLna","id":"4Yww2EYetseL1eL2YuvLna","images":[{"height":640,"url":"https://i.scdn.co/image/6639c2566040b01bbc89402ae57feb9ccee03bad","width":640},{"height":300,"url":"https://i.scdn.co/image/2405d73b6f44240342011b733f418b19dc4f7ec1","width":300},{"height":64,"url":"https://i.scdn.co/image/75ed356efc7c4bfe8c116ae79bce9ba27e92348f","width":64}],"name":"Last Year Was Complicated","release_date":"2016-06-10","release_date_precision":"day","total_tracks":12,"type":"album","uri":"spotify:album:4Yww2EYetseL1eL2YuvLna"},"artists":[{"external_urls":{"spotify":"https://open.spotify.com/artist/4Rxn7Im3LGfyRkY2FlHhWi"},"href":"https://api.spotify.com/v1/artists/4Rxn7Im3LGfyRkY2FlHhWi","id":"4Rxn7Im3LGfyRkY2FlHhWi","name":"Nick Jonas","type":"artist","uri":"spotify:artist:4Rxn7Im3LGfyRkY2FlHhWi"}],"available_markets":["AD","AR","AT","AU","BE","BG","BO","BR","CA","CH","CL","CO","CR","CY","CZ","DE","DK","DO","EC","EE","ES","FI","FR","GB","GR","GT","HK","HN","HU","ID","IE","IL","IS","IT","JP","LI","LT","LU","LV","MC","MT","MX","MY","NI","NL","NO","NZ","PA","PE","PH","PL","PT","PY","RO","SG","SK","SV","TH","TR","TW","US","UY","VN","ZA"],"disc_number":1,"duration_ms":232480,"explicit":false,"external_ids":{"isrc":"USUM71602423"},"external_urls":{"spotify":"https://open.spotify.com/track/545yZeRbrPHj6wM94RgT3M"},"href":"https://api.spotify.com/v1/tracks/545yZeRbrPHj6wM94RgT3M","id":"545yZeRbrPHj6wM94RgT3M","is_local":false,"name":"Unhinged","popularity":57,"preview_url":null,"track_number":11,"type":"track","uri":"spotify:track:545yZeRbrPHj6wM94RgT3M"},{"album":{"album_type":"album","artists":[{"external_urls":{"spotify":"https://open.spotify.com/artist/4AcHt3JxKy59IX7JNNlZn4"},"href":"https://api.spotify.com/v1/artists/4AcHt3JxKy59IX7JNNlZn4","id":"4AcHt3JxKy59IX7JNNlZn4","name":"Fitz and The Tantrums","type":"artist","uri":"spotify:artist:4AcHt3JxKy59IX7JNNlZn4"}],"available_markets":["AD","AR","AT","AU","BE","BG","BO","BR","CA","CH","CL","CO","CR","CY","CZ","DE","DK","DO","EC","EE","ES","FI","FR","GB","GR","GT","HK","HN","HU","ID","IE","IL","IS","IT","JP","LI","LT","LU","LV","MC","MT","MX","MY","NI","NL","NO","NZ","PA","PE","PH","PL","PT","PY","RO","SE","SG","SK","SV","TH","TR","TW","US","UY","VN","ZA"],"external_urls":{"spotify":"https://open.spotify.com/album/4eoIRaV8z8v2LaXQSWy2LC"},"href":"https://api.spotify.com/v1/albums/4eoIRaV8z8v2LaXQSWy2LC","id":"4eoIRaV8z8v2LaXQSWy2LC","images":[{"height":640,"url":"https://i.scdn.co/image/cf15e0b05f427f9e522a5cdcc8db6e1571acac04","width":640},{"height":300,"url":"https://i.scdn.co/image/4e6802a0b2d18276a49f51e454b0d9d9d6b5de75","width":300},{"height":64,"url":"https://i.scdn.co/image/bdb0a17bb61a2135526f56586ed15860fe254008","width":64}],"name":"Fitz and The Tantrums (Deluxe)","release_date":"2017-07-24","release_date_precision":"day","total_tracks":14,"type":"album","uri":"spotify:album:4eoIRaV8z8v2LaXQSWy2LC"},"artists":[{"external_urls":{"spotify":"https://open.spotify.com/artist/4AcHt3JxKy59IX7JNNlZn4"},"href":"https://api.spotify.com/v1/artists/4AcHt3JxKy59IX7JNNlZn4","id":"4AcHt3JxKy59IX7JNNlZn4","name":"Fitz and The Tantrums","type":"artist","uri":"spotify:artist:4AcHt3JxKy59IX7JNNlZn4"}],"available_markets":["AD","AR","AT","AU","BE","BG","BO","BR","CA","CH","CL","CO","CR","CY","CZ","DE","DK","DO","EC","EE","ES","FI","FR","GB","GR","GT","HK","HN","HU","ID","IE","IL","IS","IT","JP","LI","LT","LU","LV","MC","MT","MX","MY","NI","NL","NO","NZ","PA","PE","PH","PL","PT","PY","RO","SE","SG","SK","SV","TH","TR","TW","US","UY","VN","ZA"],"disc_number":1,"duration_ms":191453,"explicit":true,"external_ids":{"isrc":"USAT21601015"},"external_urls":{"spotify":"https://open.spotify.com/track/6qirdZqYYhHfHCcUcxL2Ow"},"href":"https://api.spotify.com/v1/tracks/6qirdZqYYhHfHCcUcxL2Ow","id":"6qirdZqYYhHfHCcUcxL2Ow","is_local":false,"name":"Complicated","popularity":47,"preview_url":"https://p.scdn.co/mp3-preview/b33805bd7069f400415e8206ad506b76c140b173?cid=d0ef11b08e9041258a97e4c3a1dc69ab","track_number":3,"type":"track","uri":"spotify:track:6qirdZqYYhHfHCcUcxL2Ow"},{"album":{"album_type":"single","artists":[{"external_urls":{"spotify":"https://open.spotify.com/artist/2Ltz77e0WzkbszFytIy6SY"},"href":"https://api.spotify.com/v1/artists/2Ltz77e0WzkbszFytIy6SY","id":"2Ltz77e0WzkbszFytIy6SY","name":"Nick Mellow","type":"artist","uri":"spotify:artist:2Ltz77e0WzkbszFytIy6SY"}],"available_markets":["AD","AR","AT","AU","BE","BG","BO","BR","CA","CH","CL","CO","CR","CY","CZ","DE","DK","DO","EC","EE","ES","FI","FR","GB","GR","GT","HK","HN","HU","ID","IE","IL","IS","IT","JP","LI","LT","LU","LV","MC","MT","MX","MY","NI","NL","NO","NZ","PA","PE","PH","PL","PT","PY","RO","SE","SG","SK","SV","TH","TR","TW","US","UY","VN","ZA"],"external_urls":{"spotify":"https://open.spotify.com/album/0Gvx3CeCRSCN588sEa3vCE"},"href":"https://api.spotify.com/v1/albums/0Gvx3CeCRSCN588sEa3vCE","id":"0Gvx3CeCRSCN588sEa3vCE","images":[{"height":640,"url":"https://i.scdn.co/image/64902d5927fb9c94734e3aef0fd48eb2c685b9ff","width":640},{"height":300,"url":"https://i.scdn.co/image/b297c540d798809edc62e740fbbafcd3a6374c5b","width":300},{"height":64,"url":"https://i.scdn.co/image/d0092fe95f556e8906db92b4d6201b1ebf0e82b5","width":64}],"name":"Complicated (Remixes)","release_date":"2018-06-22","release_date_precision":"day","total_tracks":3,"type":"album","uri":"spotify:album:0Gvx3CeCRSCN588sEa3vCE"},"artists":[{"external_urls":{"spotify":"https://open.spotify.com/artist/2Ltz77e0WzkbszFytIy6SY"},"href":"https://api.spotify.com/v1/artists/2Ltz77e0WzkbszFytIy6SY","id":"2Ltz77e0WzkbszFytIy6SY","name":"Nick Mellow","type":"artist","uri":"spotify:artist:2Ltz77e0WzkbszFytIy6SY"},{"external_urls":{"spotify":"https://open.spotify.com/artist/6qOzyug9zoGuMHTmErJ6zo"},"href":"https://api.spotify.com/v1/artists/6qOzyug9zoGuMHTmErJ6zo","id":"6qOzyug9zoGuMHTmErJ6zo","name":"Aérotique","type":"artist","uri":"spotify:artist:6qOzyug9zoGuMHTmErJ6zo"},{"external_urls":{"spotify":"https://open.spotify.com/artist/2FnjEL8SlmLe3YBFmPkV9N"},"href":"https://api.spotify.com/v1/artists/2FnjEL8SlmLe3YBFmPkV9N","id":"2FnjEL8SlmLe3YBFmPkV9N","name":"Glaceo","type":"artist","uri":"spotify:artist:2FnjEL8SlmLe3YBFmPkV9N"}],"available_markets":["AD","AR","AT","AU","BE","BG","BO","BR","CA","CH","CL","CO","CR","CY","CZ","DE","DK","DO","EC","EE","ES","FI","FR","GB","GR","GT","HK","HN","HU","ID","IE","IL","IS","IT","JP","LI","LT","LU","LV","MC","MT","MX","MY","NI","NL","NO","NZ","PA","PE","PH","PL","PT","PY","RO","SE","SG","SK","SV","TH","TR","TW","US","UY","VN","ZA"],"disc_number":1,"duration_ms":205197,"explicit":false,"external_ids":{"isrc":"CH0831700711"},"external_urls":{"spotify":"https://open.spotify.com/track/47w11QEAirqz5ViDsEAF8h"},"href":"https://api.spotify.com/v1/tracks/47w11QEAirqz5ViDsEAF8h","id":"47w11QEAirqz5ViDsEAF8h","is_local":false,"name":"Complicated - Aérotique & Glaceo Remix","popularity":54,"preview_url":"https://p.scdn.co/mp3-preview/0c2530442efa90c38c06e9c722bbd4b4a8c95332?cid=d0ef11b08e9041258a97e4c3a1dc69ab","track_number":1,"type":"track","uri":"spotify:track:47w11QEAirqz5ViDsEAF8h"},{"album":{"album_type":"single","artists":[{"external_urls":{"spotify":"https://open.spotify.com/artist/67nwj3Y5sZQLl72VNUHEYE"},"href":"https://api.spotify.com/v1/artists/67nwj3Y5sZQLl72VNUHEYE","id":"67nwj3Y5sZQLl72VNUHEYE","name":"Wale","type":"artist","uri":"spotify:artist:67nwj3Y5sZQLl72VNUHEYE"}],"available_markets":["AD","AR","AT","AU","BE","BG","BO","BR","CA","CH","CL","CO","CR","CY","CZ","DE","DK","DO","EC","EE","ES","FI","FR","GB","GR","GT","HK","HN","HU","ID","IE","IL","IS","IT","JP","LI","LT","LU","LV","MC","MT","MX","MY","NI","NL","NO","NZ","PA","PE","PH","PL","PT","PY","RO","SE","SG","SK","SV","TH","TR","TW","US","UY","VN","ZA"],"external_urls":{"spotify":"https://open.spotify.com/album/73Nno1P5AhlkdmkieYeSiR"},"href":"https://api.spotify.com/v1/albums/73Nno1P5AhlkdmkieYeSiR","id":"73Nno1P5AhlkdmkieYeSiR","images":[{"height":640,"url":"https://i.scdn.co/image/330c65fb3f5697d187490f928bb47e0160579508","width":640},{"height":300,"url":"https://i.scdn.co/image/fdd83680909ff6aa121e35f33bca6529ede041a7","width":300},{"height":64,"url":"https://i.scdn.co/image/91649162b4c8330223366a62335f0e0d16e6ef04","width":64}],"name":"It's Complicated - EP","release_date":"2018-03-13","release_date_precision":"day","total_tracks":4,"type":"album","uri":"spotify:album:73Nno1P5AhlkdmkieYeSiR"},"artists":[{"external_urls":{"spotify":"https://open.spotify.com/artist/67nwj3Y5sZQLl72VNUHEYE"},"href":"https://api.spotify.com/v1/artists/67nwj3Y5sZQLl72VNUHEYE","id":"67nwj3Y5sZQLl72VNUHEYE","name":"Wale","type":"artist","uri":"spotify:artist:67nwj3Y5sZQLl72VNUHEYE"}],"available_markets":["AD","AR","AT","AU","BE","BG","BO","BR","CA","CH","CL","CO","CR","CY","CZ","DE","DK","DO","EC","EE","ES","FI","FR","GB","GR","GT","HK","HN","HU","ID","IE","IL","IS","IT","JP","LI","LT","LU","LV","MC","MT","MX","MY","NI","NL","NO","NZ","PA","PE","PH","PL","PT","PY","RO","SE","SG","SK","SV","TH","TR","TW","US","UY","VN","ZA"],"disc_number":1,"duration_ms":220369,"explicit":true,"external_ids":{"isrc":"USUYG1188143"},"external_urls":{"spotify":"https://open.spotify.com/track/19UZxlMzaW1c1yT47j7nxg"},"href":"https://api.spotify.com/v1/tracks/19UZxlMzaW1c1yT47j7nxg","id":"19UZxlMzaW1c1yT47j7nxg","is_local":false,"name":"Effortless","popularity":55,"preview_url":"https://p.scdn.co/mp3-preview/c14047ab659a97082123ea3f6cfddacfcbcc0945?cid=d0ef11b08e9041258a97e4c3a1dc69ab","track_number":3,"type":"track","uri":"spotify:track:19UZxlMzaW1c1yT47j7nxg"},{"album":{"album_type":"album","artists":[{"external_urls":{"spotify":"https://open.spotify.com/artist/5pKCCKE2ajJHZ9KAiaK11H"},"href":"https://api.spotify.com/v1/artists/5pKCCKE2ajJHZ9KAiaK11H","id":"5pKCCKE2ajJHZ9KAiaK11H","name":"Rihanna","type":"artist","uri":"spotify:artist:5pKCCKE2ajJHZ9KAiaK11H"}],"available_markets":["CA","DK","MX","NL","NO","RO","US"],"external_urls":{"spotify":"https://open.spotify.com/album/6UHhmTLl9T1scRYLmpHcDX"},"href":"https://api.spotify.com/v1/albums/6UHhmTLl9T1scRYLmpHcDX","id":"6UHhmTLl9T1scRYLmpHcDX","images":[{"height":640,"url":"https://i.scdn.co/image/171d92deda8718bbfe2d50ddab6aaedbfb6e1283","width":640},{"height":300,"url":"https://i.scdn.co/image/ed76f8fece063e1b742dc323633c26228cd37e20","width":300},{"height":64,"url":"https://i.scdn.co/image/f8801337618946dfac7a95aad018c9ec7a02ccd6","width":64}],"name":"Loud","release_date":"2010-11-16","release_date_precision":"day","total_tracks":11,"type":"album","uri":"spotify:album:6UHhmTLl9T1scRYLmpHcDX"},"artists":[{"external_urls":{"spotify":"https://open.spotify.com/artist/5pKCCKE2ajJHZ9KAiaK11H"},"href":"https://api.spotify.com/v1/artists/5pKCCKE2ajJHZ9KAiaK11H","id":"5pKCCKE2ajJHZ9KAiaK11H","name":"Rihanna","type":"artist","uri":"spotify:artist:5pKCCKE2ajJHZ9KAiaK11H"}],"available_markets":["CA","DK","MX","NL","NO","RO","US"],"disc_number":1,"duration_ms":257506,"explicit":true,"external_ids":{"isrc":"USUM71026639"},"external_urls":{"spotify":"https://open.spotify.com/track/1q9Pv0DN4veGxV29YYn5Ev"},"href":"https://api.spotify.com/v1/tracks/1q9Pv0DN4veGxV29YYn5Ev","id":"1q9Pv0DN4veGxV29YYn5Ev","is_local":false,"name":"Complicated","popularity":46,"preview_url":null,"track_number":9,"type":"track","uri":"spotify:track:1q9Pv0DN4veGxV29YYn5Ev"},{"album":{"album_type":"album","artists":[{"external_urls":{"spotify":"https://open.spotify.com/artist/4Rxn7Im3LGfyRkY2FlHhWi"},"href":"https://api.spotify.com/v1/artists/4Rxn7Im3LGfyRkY2FlHhWi","id":"4Rxn7Im3LGfyRkY2FlHhWi","name":"Nick Jonas","type":"artist","uri":"spotify:artist:4Rxn7Im3LGfyRkY2FlHhWi"}],"available_markets":["AD","AR","AT","AU","BE","BG","BO","BR","CA","CH","CL","CO","CR","CY","CZ","DE","DK","DO","EC","EE","ES","FI","FR","GB","GR","GT","HK","HN","HU","ID","IE","IL","IS","IT","JP","LI","LT","LU","LV","MC","MT","MX","MY","NI","NL","NO","NZ","PA","PE","PH","PL","PT","PY","RO","SG","SK","SV","TH","TR","TW","US","UY","VN","ZA"],"external_urls":{"spotify":"https://open.spotify.com/album/4Yww2EYetseL1eL2YuvLna"},"href":"https://api.spotify.com/v1/albums/4Yww2EYetseL1eL2YuvLna","id":"4Yww2EYetseL1eL2YuvLna","images":[{"height":640,"url":"https://i.scdn.co/image/6639c2566040b01bbc89402ae57feb9ccee03bad","width":640},{"height":300,"url":"https://i.scdn.co/image/2405d73b6f44240342011b733f418b19dc4f7ec1","width":300},{"height":64,"url":"https://i.scdn.co/image/75ed356efc7c4bfe8c116ae79bce9ba27e92348f","width":64}],"name":"Last Year Was Complicated","release_date":"2016-06-10","release_date_precision":"day","total_tracks":12,"type":"album","uri":"spotify:album:4Yww2EYetseL1eL2YuvLna"},"artists":[{"external_urls":{"spotify":"https://open.spotify.com/artist/4Rxn7Im3LGfyRkY2FlHhWi"},"href":"https://api.spotify.com/v1/artists/4Rxn7Im3LGfyRkY2FlHhWi","id":"4Rxn7Im3LGfyRkY2FlHhWi","name":"Nick Jonas","type":"artist","uri":"spotify:artist:4Rxn7Im3LGfyRkY2FlHhWi"}],"available_markets":["AD","AR","AT","AU","BE","BG","BO","BR","CA","CH","CL","CO","CR","CY","CZ","DE","DK","DO","EC","EE","ES","FI","FR","GB","GR","GT","HK","HN","HU","ID","IE","IL","IS","IT","JP","LI","LT","LU","LV","MC","MT","MX","MY","NI","NL","NO","NZ","PA","PE","PH","PL","PT","PY","RO","SG","SK","SV","TH","TR","TW","US","UY","VN","ZA"],"disc_number":1,"duration_ms":192680,"explicit":false,"external_ids":{"isrc":"USUM71602393"},"external_urls":{"spotify":"https://open.spotify.com/track/0HqkqqlMMKeyhC3I7mNV7b"},"href":"https://api.spotify.com/v1/tracks/0HqkqqlMMKeyhC3I7mNV7b","id":"0HqkqqlMMKeyhC3I7mNV7b","is_local":false,"name":"Champagne Problems","popularity":54,"preview_url":null,"track_number":2,"type":"track","uri":"spotify:track:0HqkqqlMMKeyhC3I7mNV7b"},{"album":{"album_type":"single","artists":[{"external_urls":{"spotify":"https://open.spotify.com/artist/67nwj3Y5sZQLl72VNUHEYE"},"href":"https://api.spotify.com/v1/artists/67nwj3Y5sZQLl72VNUHEYE","id":"67nwj3Y5sZQLl72VNUHEYE","name":"Wale","type":"artist","uri":"spotify:artist:67nwj3Y5sZQLl72VNUHEYE"}],"available_markets":["AD","AR","AT","AU","BE","BG","BO","BR","CA","CH","CL","CO","CR","CY","CZ","DE","DK","DO","EC","EE","ES","FI","FR","GB","GR","GT","HK","HN","HU","ID","IE","IL","IS","IT","JP","LI","LT","LU","LV","MC","MT","MX","MY","NI","NL","NO","NZ","PA","PE","PH","PL","PT","PY","RO","SE","SG","SK","SV","TH","TR","TW","US","UY","VN","ZA"],"external_urls":{"spotify":"https://open.spotify.com/album/73Nno1P5AhlkdmkieYeSiR"},"href":"https://api.spotify.com/v1/albums/73Nno1P5AhlkdmkieYeSiR","id":"73Nno1P5AhlkdmkieYeSiR","images":[{"height":640,"url":"https://i.scdn.co/image/330c65fb3f5697d187490f928bb47e0160579508","width":640},{"height":300,"url":"https://i.scdn.co/image/fdd83680909ff6aa121e35f33bca6529ede041a7","width":300},{"height":64,"url":"https://i.scdn.co/image/91649162b4c8330223366a62335f0e0d16e6ef04","width":64}],"name":"It's Complicated - EP","release_date":"2018-03-13","release_date_precision":"day","total_tracks":4,"type":"album","uri":"spotify:album:73Nno1P5AhlkdmkieYeSiR"},"artists":[{"external_urls":{"spotify":"https://open.spotify.com/artist/67nwj3Y5sZQLl72VNUHEYE"},"href":"https://api.spotify.com/v1/artists/67nwj3Y5sZQLl72VNUHEYE","id":"67nwj3Y5sZQLl72VNUHEYE","name":"Wale","type":"artist","uri":"spotify:artist:67nwj3Y5sZQLl72VNUHEYE"}],"available_markets":["AD","AR","AT","AU","BE","BG","BO","BR","CA","CH","CL","CO","CR","CY","CZ","DE","DK","DO","EC","EE","ES","FI","FR","GB","GR","GT","HK","HN","HU","ID","IE","IL","IS","IT","JP","LI","LT","LU","LV","MC","MT","MX","MY","NI","NL","NO","NZ","PA","PE","PH","PL","PT","PY","RO","SE","SG","SK","SV","TH","TR","TW","US","UY","VN","ZA"],"disc_number":1,"duration_ms":199185,"explicit":true,"external_ids":{"isrc":"USUYG1188141"},"external_urls":{"spotify":"https://open.spotify.com/track/3VgKiVJi6feRzebn1kwPtS"},"href":"https://api.spotify.com/v1/tracks/3VgKiVJi6feRzebn1kwPtS","id":"3VgKiVJi6feRzebn1kwPtS","is_local":false,"name":"It's Complicated","popularity":45,"preview_url":"https://p.scdn.co/mp3-preview/2b194a093ce4517447eecf586d0617e4d27e446c?cid=d0ef11b08e9041258a97e4c3a1dc69ab","track_number":1,"type":"track","uri":"spotify:track:3VgKiVJi6feRzebn1kwPtS"},{"album":{"album_type":"single","artists":[{"external_urls":{"spotify":"https://open.spotify.com/artist/1BhWF9W2PngtPSyobKg0rP"},"href":"https://api.spotify.com/v1/artists/1BhWF9W2PngtPSyobKg0rP","id":"1BhWF9W2PngtPSyobKg0rP","name":"Pia Mia","type":"artist","uri":"spotify:artist:1BhWF9W2PngtPSyobKg0rP"}],"available_markets":["AD","AR","AT","AU","BE","BG","BO","BR","CA","CH","CL","CO","CR","CY","CZ","DE","DK","DO","EC","EE","ES","FI","FR","GR","GT","HK","HN","HU","ID","IL","IS","IT","JP","LI","LT","LU","LV","MC","MT","MX","MY","NI","NL","NO","NZ","PA","PE","PH","PL","PT","PY","RO","SE","SG","SK","SV","TH","TR","TW","US","UY","VN","ZA"],"external_urls":{"spotify":"https://open.spotify.com/album/3sHGkl7UfE9JGDLv5sC7H5"},"href":"https://api.spotify.com/v1/albums/3sHGkl7UfE9JGDLv5sC7H5","id":"3sHGkl7UfE9JGDLv5sC7H5","images":[{"height":640,"url":"https://i.scdn.co/image/b77695cd5e323d0c4c6eec033ed4bc7bcd80fa8d","width":640},{"height":300,"url":"https://i.scdn.co/image/17c0d2731260ed808568f3d62ea3372d2565a07f","width":300},{"height":64,"url":"https://i.scdn.co/image/7e9fa4fba4c886ad7de5bfee2583e909e46bf971","width":64}],"name":"The Gift","release_date":"2014-01-01","release_date_precision":"day","total_tracks":6,"type":"album","uri":"spotify:album:3sHGkl7UfE9JGDLv5sC7H5"},"artists":[{"external_urls":{"spotify":"https://open.spotify.com/artist/1BhWF9W2PngtPSyobKg0rP"},"href":"https://api.spotify.com/v1/artists/1BhWF9W2PngtPSyobKg0rP","id":"1BhWF9W2PngtPSyobKg0rP","name":"Pia Mia","type":"artist","uri":"spotify:artist:1BhWF9W2PngtPSyobKg0rP"}],"available_markets":["AD","AR","AT","AU","BE","BG","BO","BR","CA","CH","CL","CO","CR","CY","CZ","DE","DK","DO","EC","EE","ES","FI","FR","GR","GT","HK","HN","HU","ID","IL","IS","IT","JP","LI","LT","LU","LV","MC","MT","MX","MY","NI","NL","NO","NZ","PA","PE","PH","PL","PT","PY","RO","SE","SG","SK","SV","TH","TR","TW","US","UY","VN","ZA"],"disc_number":1,"duration_ms":220280,"explicit":false,"external_ids":{"isrc":"USUM71400941"},"external_urls":{"spotify":"https://open.spotify.com/track/49Z9Ezt12L0ldT5hRfhOEv"},"href":"https://api.spotify.com/v1/tracks/49Z9Ezt12L0ldT5hRfhOEv","id":"49Z9Ezt12L0ldT5hRfhOEv","is_local":false,"name":"Complicated","popularity":46,"preview_url":null,"track_number":2,"type":"track","uri":"spotify:track:49Z9Ezt12L0ldT5hRfhOEv"},{"album":{"album_type":"single","artists":[{"external_urls":{"spotify":"https://open.spotify.com/artist/1AqQ7buD0q6SRbQtYQUnou"},"href":"https://api.spotify.com/v1/artists/1AqQ7buD0q6SRbQtYQUnou","id":"1AqQ7buD0q6SRbQtYQUnou","name":"Alex Mattson","type":"artist","uri":"spotify:artist:1AqQ7buD0q6SRbQtYQUnou"}],"available_markets":["AD","AR","AT","AU","BE","BG","BO","BR","CA","CH","CL","CO","CR","CY","CZ","DE","DK","DO","EC","EE","ES","FI","FR","GB","GR","GT","HK","HN","HU","ID","IE","IL","IS","IT","JP","LI","LT","LU","LV","MC","MT","MX","MY","NI","NL","NO","NZ","PA","PE","PH","PL","PT","PY","RO","SE","SG","SK","SV","TH","TR","TW","US","UY","VN","ZA"],"external_urls":{"spotify":"https://open.spotify.com/album/7zclxjoAcIhfs1TA8VwycT"},"href":"https://api.spotify.com/v1/albums/7zclxjoAcIhfs1TA8VwycT","id":"7zclxjoAcIhfs1TA8VwycT","images":[{"height":640,"url":"https://i.scdn.co/image/ea2bb4b683d4220a4c7a8da9b089722c6f38b1d1","width":640},{"height":300,"url":"https://i.scdn.co/image/bbfc64a33f8a9fec9404f3840bfc0cbe6a9f78f3","width":300},{"height":64,"url":"https://i.scdn.co/image/26d11a7d22c91c64bf218e63a427ab1f449f20b7","width":64}],"name":"Complicated Love","release_date":"2018-02-23","release_date_precision":"day","total_tracks":1,"type":"album","uri":"spotify:album:7zclxjoAcIhfs1TA8VwycT"},"artists":[{"external_urls":{"spotify":"https://open.spotify.com/artist/1AqQ7buD0q6SRbQtYQUnou"},"href":"https://api.spotify.com/v1/artists/1AqQ7buD0q6SRbQtYQUnou","id":"1AqQ7buD0q6SRbQtYQUnou","name":"Alex Mattson","type":"artist","uri":"spotify:artist:1AqQ7buD0q6SRbQtYQUnou"}],"available_markets":["AD","AR","AT","AU","BE","BG","BO","BR","CA","CH","CL","CO","CR","CY","CZ","DE","DK","DO","EC","EE","ES","FI","FR","GB","GR","GT","HK","HN","HU","ID","IE","IL","IS","IT","JP","LI","LT","LU","LV","MC","MT","MX","MY","NI","NL","NO","NZ","PA","PE","PH","PL","PT","PY","RO","SE","SG","SK","SV","TH","TR","TW","US","UY","VN","ZA"],"disc_number":1,"duration_ms":160587,"explicit":false,"external_ids":{"isrc":"FIBAR1800032"},"external_urls":{"spotify":"https://open.spotify.com/track/1wdAHxgIaXECOYOHgseniK"},"href":"https://api.spotify.com/v1/tracks/1wdAHxgIaXECOYOHgseniK","id":"1wdAHxgIaXECOYOHgseniK","is_local":false,"name":"Complicated Love","popularity":54,"preview_url":"https://p.scdn.co/mp3-preview/b6dff0df7d3baf6802f3418b1a9746eae438ae56?cid=d0ef11b08e9041258a97e4c3a1dc69ab","track_number":1,"type":"track","uri":"spotify:track:1wdAHxgIaXECOYOHgseniK"}],"limit":20,"next":"https://api.spotify.com/v1/search?query=complicated&type=track&offset=20&limit=20","offset":0,"previous":null,"total":4894}}